aliyunsdksts/__init__.py
aliyunsdksts/endpoint.py
aliyunsdksts/request/__init__.py
aliyunsdksts/request/v20150401/AssumeRoleRequest.py
aliyunsdksts/request/v20150401/AssumeRoleWithOIDCRequest.py
aliyunsdksts/request/v20150401/AssumeRoleWithSAMLRequest.py
aliyunsdksts/request/v20150401/GetCallerIdentityRequest.py
aliyunsdksts/request/v20150401/__init__.py
aliyun_python_sdk_sts-3.1.3.dist-info/LICENSE
aliyun_python_sdk_sts-3.1.3.dist-info/METADATA
aliyun_python_sdk_sts-3.1.3.dist-info/WHEEL
aliyun_python_sdk_sts-3.1.3.dist-info/top_level.txt
aliyun_python_sdk_sts-3.1.3.dist-info/RECORD
